genetic_collections/__init__.py
genetic_collections/cli.py
genetic_collections/ncbi_functions.py
genetic_collections-0.1.9.dist-info/DESCRIPTION.rst
genetic_collections-0.1.9.dist-info/METADATA
genetic_collections-0.1.9.dist-info/RECORD
genetic_collections-0.1.9.dist-info/WHEEL
genetic_collections-0.1.9.dist-info/entry_points.txt
genetic_collections-0.1.9.dist-info/metadata.json
genetic_collections-0.1.9.dist-info/top_level.txt
