Metadata-Version: 2.0
Name: genetic-collections
Version: 0.1.9
Summary: A Python library for connecting genetic records with specimen data.
Home-page: https://github.com/MikeTrizna/genetic_collections
Author: Mike Trizna
Author-email: mike.trizna@gmail.com
License: MIT license
Keywords: genetic_collections
Platform: UNKNOWN
Classifier: Development Status :: 2 - Pre-Alpha
Classifier: Intended Audience :: Developers
Classifier: License :: OSI Approved :: MIT License
Classifier: Natural Language :: English
Classifier: Programming Language :: Python :: 3
Classifier: Programming Language :: Python :: 3.5
Classifier: Programming Language :: Python :: 3.6
Requires-Dist: requests
Requires-Dist: pandas
Requires-Dist: lxml
Requires-Dist: tqdm
